{
    "1":  { "branches": ["N","S"] },
    "2":  { "branches": ["E","W"] },
    "3":  { "branches": ["N","E"] },
    "4":  { "branches": ["S","W"] },
    "5":  { "branches": ["N","W"] },
    "6":  { "branches": ["E","S"] },
    "7":  { "branches": ["N","E","S"] },
    "8":  { "branches": ["E","S","W"] },
    "9":  { "branches": ["N","E","W"] },
    "10":  { "branches": ["N","S","W"] },
    "11":  { "branches": ["N","E","W","S"] },
    "12":  { "branches": ["N","E","W","S"] },
    "13":  { "branches": ["N","S"] },
    "14":  { "branches": ["E","W"] },
    "15":  { "branches": ["N","E"] },
    "16":  { "branches": ["S","W"] },
    "17":  { "branches": ["N","W"] },
    "18":  { "branches": ["E","S"] },
    "19":  { "branches": ["N","E","S"] },
    "20":  { "branches": ["E","S","W"] },
    "21":  { "branches": ["N","E","W"] },
    "22":  { "branches": ["N","S","W"] },
    "23":  { "branches": ["N","E","W","S"] },
    "24":  { "branches": ["N","E","W","S"] },
    "25":  { "branches": ["N","S"] },
    "26":  { "branches": ["E","W"] },
    "27":  { "branches": ["N","E"] },
    "28":  { "branches": ["S","W"] },
    "29":  { "branches": ["N","W"] },
    "30":  { "branches": ["E","S"] },
    "31":  { "branches": ["N","E","S"] },
    "32":  { "branches": ["E","S","W"] },
    "33":  { "branches": ["N","E","W"] },
    "34":  { "branches": ["N","S","W"] },
    "35":  { "branches": ["N","E","W","S"] },
    "36":  { "branches": ["N","E","W","S"] }
}